README.md
setup.py
jaxxstorm_pulumi_aws_securebaseline/__init__.py
jaxxstorm_pulumi_aws_securebaseline/_utilities.py
jaxxstorm_pulumi_aws_securebaseline/cloudwatch_api_audit.py
jaxxstorm_pulumi_aws_securebaseline/iam.py
jaxxstorm_pulumi_aws_securebaseline/provider.py
jaxxstorm_pulumi_aws_securebaseline/pulumi-plugin.json
jaxxstorm_pulumi_aws_securebaseline/py.typed
jaxxstorm_pulumi_aws_securebaseline/vpc.py
jaxxstorm_pulumi_aws_securebaseline.egg-info/PKG-INFO
jaxxstorm_pulumi_aws_securebaseline.egg-info/SOURCES.txt
jaxxstorm_pulumi_aws_securebaseline.egg-info/dependency_links.txt
jaxxstorm_pulumi_aws_securebaseline.egg-info/not-zip-safe
jaxxstorm_pulumi_aws_securebaseline.egg-info/requires.txt
jaxxstorm_pulumi_aws_securebaseline.egg-info/top_level.txt