Metadata-Version: 2.1
Name: jaxxstorm-pulumi-aws-securebaseline
Version: 0.0.0
Summary: UNKNOWN
Home-page: UNKNOWN
License: UNKNOWN
Platform: UNKNOWN
